ai_french_kiss_video_generator/__init__.py
ai_french_kiss_video_generator-1768790.361.726.dist-info/licenses/LICENSE
ai_french_kiss_video_generator-1768790.361.726.dist-info/METADATA
ai_french_kiss_video_generator-1768790.361.726.dist-info/WHEEL
ai_french_kiss_video_generator-1768790.361.726.dist-info/top_level.txt
ai_french_kiss_video_generator-1768790.361.726.dist-info/RECORD
